dramatiq_abort/__init__.py
dramatiq_abort/abort_manager.py
dramatiq_abort/backend.py
dramatiq_abort/middleware.py
dramatiq_abort/backends/__init__.py
dramatiq_abort/backends/redis.py
dramatiq_abort/backends/stub.py
dramatiq_abort-1.2.1.dist-info/LICENSE
dramatiq_abort-1.2.1.dist-info/METADATA
dramatiq_abort-1.2.1.dist-info/WHEEL
dramatiq_abort-1.2.1.dist-info/top_level.txt
dramatiq_abort-1.2.1.dist-info/RECORD
