Metadata-Version: 2.1
Name: dramatiq-abort
Version: 1.2.1
Summary: Dramatiq middleware to abort tasks.
Home-page: https://github.com/flared/dramatiq-abort
Author: Flare Systems Inc.
Author-email: oss@flare.systems
Classifier: Programming Language :: Python :: 3.8
Classifier: Programming Language :: Python :: 3.9
Classifier: Programming Language :: Python :: 3.10
Classifier: Programming Language :: Python :: 3.11
Classifier: Programming Language :: Python :: 3.12
Classifier: Programming Language :: Python :: 3.13
Classifier: Programming Language :: Python :: 3 :: Only
Classifier: Development Status :: 4 - Beta
Classifier: Topic :: System :: Distributed Computing
Classifier: License :: OSI Approved :: GNU Lesser General Public License v3 or later (LGPLv3+)
License-File: LICENSE
Requires-Dist: dramatiq
Provides-Extra: gevent
Requires-Dist: gevent>=1.1; extra == "gevent"
Provides-Extra: redis
Requires-Dist: redis<6.0,>=2.0; extra == "redis"
Provides-Extra: all
Requires-Dist: gevent>=1.1; extra == "all"
Requires-Dist: redis<6.0,>=2.0; extra == "all"
Provides-Extra: dev
Requires-Dist: gevent>=1.1; extra == "dev"
Requires-Dist: redis<6.0,>=2.0; extra == "dev"
Requires-Dist: flake8; extra == "dev"
Requires-Dist: flake8-bugbear; extra == "dev"
Requires-Dist: flake8-quotes; extra == "dev"
Requires-Dist: isort; extra == "dev"
Requires-Dist: mypy; extra == "dev"
Requires-Dist: types-redis; extra == "dev"
Requires-Dist: black; extra == "dev"
Requires-Dist: pytest; extra == "dev"
Requires-Dist: pytest-cov; extra == "dev"
Requires-Dist: tox>=3.14.0; extra == "dev"
Requires-Dist: sphinx; extra == "dev"
Requires-Dist: sphinx-autodoc-typehints; extra == "dev"
Requires-Dist: build; extra == "dev"
Requires-Dist: wheel; extra == "dev"
Requires-Dist: twine; extra == "dev"
